{
  "url": "https://stripe.com/br/resources/more/accounting-reconciliation-101",
  "method": "fetch",
  "title": "Reconciliação contábil: o que é e como fazer | StripeRevenue Recognition",
  "sections": [
    {
      "anchorId": "o-que-e-reconciliacao-em-contabilidade",
      "heading": "O que é reconciliação em contabilidade?",
      "bodyMd": "Em contabilidade, a reconciliação é o processo de comparar dois conjuntos de registros ou informações financeiras, como extratos bancários, contas do livro-razão ou outros registros relevantes, para garantir sua precisão e uniformidade.\n\nO principal objetivo da reconciliação é identificar e resolver quaisquer discrepâncias entre os dois conjuntos de registros. Isso ajuda a preservar a integridade das demonstrações financeiras e identifica erros ou atividades fraudulentas."
    },
    {
      "anchorId": "tipos-de-reconciliacao-contabil",
      "heading": "Tipos de reconciliação contábil",
      "bodyMd": "A reconciliação contábil envolve a comparação e verificação de transações financeiras e saldos para identificar e resolver discrepâncias. Estes são os tipos de reconciliação contábil:\n\n*   **Reconciliação bancária**  \n    Comparar as transações e saldos no extrato bancário de uma empresa com os lançamentos no livro caixa ou livro-razão\n    \n*   **Reconciliação de contas a receber**  \n    Comparar os saldos de contas a receber com documentação de apoio, como faturas de clientes e recibos de pagamento\n    \n*   **Reconciliação de contas a pagar**  \n    Comparar os saldos de contas a pagar com faturas e registros de pagamento de fornecedores\n    \n*   **Conciliação entre empresas**  \n    Reconciliar transações entre empresas e saldos entre subsidiárias ou divisões para manter a precisão e eliminar erros\n    \n*   **Reconciliação de estoque**  \n    Comparar os números do estoque físico com os saldos em registro para identificar discrepâncias e resolver problemas como roubo ou erros de registro\n    \n*   **Reconciliação do livro-razão**  \n    Reconciliar várias contas do livro-razão para garantir que as transações e os saldos registrados estejam completos e precisos\n    \n*   **Reconciliação de ativos fixos**  \n    Verificar registros de ativos fixos comparando-os com faturas de compra, cronogramas de depreciação e registros de descarte\n    \n*   **Reconciliação fiscal**  \n    Comparar registros fiscais, como imposto sobre vendas ou imposto de renda, com registros financeiros correspondentes para garantir que a declaração de obrigações fiscais esteja em dia\n    \n*   **Reconciliação de cartões de crédito e débito**  \n    Comparar transações registradas em extratos de cartão de crédito ou débito com registros financeiros para garantir precisão e integridade\n    \n*   **Reconciliação de carteira digital**  \n    Verificação de [transações em carteiras digitais](https://stripe.com/br/resources/more/digital-wallets-101) com os registros financeiros da empresa\n    \n*   **Reconciliação global de moedas**  \n    Assegurar a exatidão das [transações em moeda estrangeira](https://stripe.com/br/resources/more/cross-border-payments-explained), comparando-os com as taxas de câmbio e os registros financeiros\n    \n*   **Reconciliação automática de pagamentos em tempo real**  \n    Automatizar processos de reconciliação de pagamentos em tempo real para combinar e reconciliar pagamentos com precisão e eficiência\n    \n\nEsses diferentes tipos de reconciliação são importantes para manter registros financeiros precisos, detectar erros e fraudes e garantir a confiabilidade do sistema contábil. Eles esclarecem a posição financeira da organização, permitindo tomar decisões de negócios bem informadas."
    },
    {
      "anchorId": "por-que-a-reconciliacao-contabil-e-importante-para-as-empresas",
      "heading": "Por que a reconciliação contábil é importante para as empresas",
      "bodyMd": "A reconciliação contábil é essencial para as empresas. Veja o porquê:\n\n*   **Registros financeiros precisos**  \n    Comparando diferentes conjuntos de dados, a reconciliação garante que os registros financeiros sejam precisos e confiáveis. Quando uma empresa processa ou registra transações financeiras, podem ocorrer discrepâncias, erros e omissões. A reconciliação ajuda a identificar e corrigir essas discrepâncias. Isso garante que as demonstrações financeiras e relatórios apresentem uma visão precisa e justa da posição financeira da empresa.\n    \n*   **Detecção de fraudes**  \n    A reconciliação é um mecanismo essencial de controle interno para [detectar fraudes](https://stripe.com/br/resources/more/payment-fraud-detection). Ao comparar registros como extratos bancários, faturas e recibos de pagamento, as empresas podem identificar discrepâncias ou irregularidades que podem indicar transações fraudulentas, protegendo assim o patrimônio e os interesses financeiros da empresa.\n    \n*   **Processo decisório**  \n    A reconciliação garante que os dados usados para tomar decisões sejam confiáveis e completos. Ao conciliar diferentes contas e registros financeiros, as empresas ganham confiança na precisão de suas informações, o que lhes permite tomar decisões estratégicas com base em insights financeiros sólidos.\n    \n*   **Conformidade e requisitos legais**  \n    A reconciliação ajuda as empresas a cumprir obrigações legais e de conformidade. Por exemplo, com reconciliação bancária precisa, uma empresa pode assegurar a conformidade com padrões de auditoria e criar demonstrações financeiras que cumpram diretrizes regulatórias. A falta de reconciliação adequada das contas pode gerar não conformidade, multas ou consequências jurídicas.\n    \n*   **Gestão de riscos**  \n    A reconciliação ajuda a gerenciar riscos financeiros identificando erros, discrepâncias ou irregularidades imediatamente. Ao reconciliar as contas, as empresas podem detectar riscos, como problemas de fluxo de caixa, discrepâncias de estoque e cálculos fiscais incorretos. A identificação antecipada dos riscos permite que as empresas tomem as medidas adequadas e protejam sua estabilidade financeira.\n    \n*   **Estabelecer a confiança dos stakeholders**  \n    A reconciliação significa que as demonstrações financeiras são preparadas com integridade e transparência, o que gera confiança e credibilidade entre as partes interessadas, como investidores, credores e acionistas. Essa confiança fortalece a reputação do negócio e aumenta a confiança em sua saúde financeira."
    },
    {
      "anchorId": "praticas-recomendadas-de-reconciliacao-contabil",
      "heading": "Práticas recomendadas de reconciliação contábil",
      "bodyMd": "Seguindo essas práticas recomendadas de conciliação contábil, as empresas podem melhorar a precisão dos registros financeiros, fortalecer os controles internos, detectar e prevenir fraudes e manter a conformidade com requisitos regulatórios. Essas práticas contribuem para relatórios financeiros confiáveis, que são parte integrante de quase todos os aspectos da operação e do crescimento de um negócio.\n\nPráticas recomendadas de reconciliação contábil para empresas:\n\n*   **Reconciliação regular**  \n    Faça reconciliações regularmente, de preferência mensais ou com a frequência que for necessária para o volume de transações. Se a empresa fizer reconciliações frequentes e disciplinadas, pode identificar e resolver discrepâncias rapidamente, antes que elas causem problemas no futuro.\n    \n*   **Documentação e registros**  \n    Mantenha documentação detalhada do processo de reconciliação, incluindo extratos bancários, faturas, recibos e outros registros relevantes. A documentação adequada do processo de reconciliação facilita auditorias ou revisões futuras e ajuda a identificar e resolver discrepâncias.\n    \n*   **Segregação de funções**  \n    Implemente a segregação de funções para garantir que diferentes pessoas sejam responsáveis por diferentes aspectos do processo, como registrar, reconciliar e aprovar transações financeiras. Com essa separação, pessoas diferentes analisam e revisam as informações financeiras em diferentes momentos do processo, ajudando a prevenir erros e fraudes.\n    \n*   **Procedimentos claros de reconciliação**  \n    Estabeleça procedimentos padronizados de reconciliação, definindo claramente as etapas, funções e responsabilidades apropriadas dos indivíduos e prazos específicos. Procedimentos claros promovem disciplina, minimizam erros e garantem que o processo de reconciliação seja conduzido de forma organizada.\n    \n*   **Automação da reconciliação**  \n    Sempre que possível, utilize softwares contábeis ou ferramentas de reconciliação para automatizar o processo. A automação reduz erros manuais, melhora a eficiência e fornece uma estrutura sistemática para a reconciliação de contas e registros.\n    \n*   **Comparação e investigação**  \n    Realize uma comparação completa dos registros financeiros, identificando eventuais discrepâncias. Investigue e resolva essas discrepâncias rapidamente, rastreando as causas raiz, corrigindo erros e ajustando os registros financeiros conforme necessário. Uma investigação adequada ajuda a evitar erros recorrentes e garantir que as informações financeiras sejam precisas.\n    \n*   **Comunicação contínua**  \n    Promova comunicação aberta entre departamentos e pessoas relevantes no processo de reconciliação. A comunicação ajuda a resolver problemas, esclarecer dúvidas e compartilhar informações de forma eficaz. Um processo de reconciliação abrangente e preciso depende da colaboração e coordenação entre as diferentes partes interessadas.\n    \n*   **Revisão e aprovação de reconciliações**  \n    Implemente um processo de revisão e aprovação para garantir uma revisão independente dos registros reconciliados. Este processo deve incluir a análise da exatidão e adequação dos saldos reconciliados e a investigação de eventuais discrepâncias significativas. A aprovação por uma autoridade designada traz mais uma garantia para o processo de reconciliação.\n    \n*   **Melhoria contínua**  \n    Avalie e aprimore o processo de reconciliação regularmente, identificando áreas para melhoria. Analise padrões de discrepâncias, identifique pontos fracos e implemente melhorias para prevenir erros futuros. Ao refinar continuamente o processo de reconciliação, as empresas podem maximizar a precisão, a eficiência e o controle financeiro geral."
    },
    {
      "anchorId": "reconciliacao-contabil-com-a-stripe",
      "heading": "Reconciliação contábil com a Stripe",
      "bodyMd": "A [Stripe oferece uma solução avançada de reconciliação](https://stripe.com/br/docs/reconciliation/overview) que simplifica o processo para as empresas. A solução de reconciliação da Stripe automatiza o processo de reconciliação para empresas e oferece uma visão abrangente da sua movimentação financeira.\n\nO processo de reconciliação da Stripe compara os registros internos da empresa, como faturas, com os registros externos, como arquivos de liquidação, arquivos de repasses e extratos bancários. O sistema automatizado da Stripe gerencia essa comparação, permitindo capturar receitas com precisão e reconciliar seus sistemas internos de contabilidade com cobranças e reembolsos processados Stripe nível de transação.\n\nA solução de reconciliação Stripe oferece vários benefícios para as empresas:\n\n*   Permite que você acompanhe seu caixa diariamente, alinhando os registros financeiros e os fundos recebidos. Identificando lacunas nos fluxos de fundos ou discrepâncias de dados, é possível resolver erros rapidamente e minimizar perdas financeiras.\n    \n*   A reconciliação da Stripe dá visibilidade de todo o ciclo de cada transação. É fácil rastrear e monitorar o fluxo de fundos, garantindo que cada transação seja registrada e contabilizada com precisão. Esse nível de transparência ajuda a proteger sua empresa, identificando erros ou irregularidades.\n    \n*   A reconciliação da Stripe é muito vantajosa para empresas com alto volume de transações. Se a sua empresa processa milhares de transações todos os meses, a automação e a flexibilidade da solução de reconciliação da Stripe podem otimizar suas operações financeiras.\n    \n*   Se a sua empresa tem ambientes de transação complexos, como ciclos longos distribuídos por vários períodos, ou clientes que usam várias formas de pagamento na mesma transação, a solução de reconciliação da Stripe gerencia essas complexidades de forma eficaz. Ela fornece a flexibilidade e a precisão necessárias para reconciliar diversos tipos de transações e garantir relatórios financeiros precisos.\n    \n\nA solução de reconciliação da Stripe automatiza e simplifica o processo de comparação de registros internos com registros externos, permitindo que as empresas capturem receita com precisão, acompanhem o fluxo de caixa, identifiquem discrepâncias e implementem controles financeiros robustos. Se você tem grandes volumes de transações ou cenários complexos de transações, a solução de reconciliação da Stripe oferece suporte escalável e confiável para suas operações financeiras. Para saber mais ou começar, acesse [aqui](https://stripe.com/br/contact/sales)."
    }
  ],
  "scrapedAt": "2026-06-22T12:59:54.686Z",
  "sourceUrl": "https://stripe.com/br/resources/more/accounting-reconciliation-101"
}